HL7reporting/__init__.py
HL7reporting/supporting/Message_Corrector_Key.xlsx
HL7reporting/supporting/NSSP_Element_Reader.xlsx
HL7reporting/supporting/NSSP_Validity_Reader.xlsx
HL7reporting-0.1.2.dist-info/METADATA
HL7reporting-0.1.2.dist-info/WHEEL
HL7reporting-0.1.2.dist-info/top_level.txt
HL7reporting-0.1.2.dist-info/RECORD
