Metadata-Version: 2.1
Name: HL7reporting
Version: 0.1.2
Summary: A package designed to improve HL7 Data Quality reporting in the field of public health informatics.
Home-page: https://github.com/pjgibson25/locate-nssp-elements
Author: PJ Gibson
Author-email: pjgibson25@gmail.com
License: UNKNOWN
Platform: UNKNOWN
Classifier: Programming Language :: Python :: 3
Classifier: License :: OSI Approved :: MIT License
Classifier: Operating System :: OS Independent
Requires-Python: >=3.8
